LICENSE.txt
README.md
setup.cfg
setup.py
incf/__init__.py
incf.countryutils2.egg-info/PKG-INFO
incf.countryutils2.egg-info/SOURCES.txt
incf.countryutils2.egg-info/dependency_links.txt
incf.countryutils2.egg-info/entry_points.txt
incf.countryutils2.egg-info/namespace_packages.txt
incf.countryutils2.egg-info/not-zip-safe
incf.countryutils2.egg-info/requires.txt
incf.countryutils2.egg-info/top_level.txt
incf/countryutils/__init__.py
incf/countryutils/data.py
incf/countryutils/datatypes.py
incf/countryutils/prepare_data.py
incf/countryutils/tests.py
incf/countryutils/transformations.py