Metadata-Version: 2.1
Name: incf.countryutils2
Version: 1.2
Summary: A convenience API for transformations between different ISO 3166 country codes.
Home-page: https://github.com/wyldebeast-wunderliebe/incf.countryutils/
Author: Raphael Ritz
Author-email: raphael.ritz@incf.org
License: BSD
Keywords: Python 'ISO 3166' 'country codes'
Platform: UNKNOWN
Classifier: Programming Language :: Python
Classifier: Topic :: Software Development :: Libraries :: Python Modules
License-File: LICENSE.txt
